ffiec_call_reports/__init__.py
ffiec_call_reports/client.py
ffiec_call_reports/models.py
ffiec_call_reports/utils.py
ffiec_call_reports-0.1.1.dist-info/licenses/LICENSE
ffiec_call_reports-0.1.1.dist-info/METADATA
ffiec_call_reports-0.1.1.dist-info/WHEEL
ffiec_call_reports-0.1.1.dist-info/top_level.txt
ffiec_call_reports-0.1.1.dist-info/RECORD
