Metadata-Version: 2.4
Name: ffiec-call-reports
Version: 0.1.1
Summary: A Python library for downloading and processing FFIEC Call Reports
Home-page: https://github.com/yourusername/ffiec_call_reports
Author: Mayank Bambal
Author-email: your.email@example.com
Project-URL: Documentation, https://github.com/yourusername/ffiec_call_reports#readme
Project-URL: Source, https://github.com/yourusername/ffiec_call_reports
Project-URL: Tracker, https://github.com/yourusername/ffiec_call_reports/issues
Keywords: ffiec,call-reports,banking,financial-data,xbrl
Classifier: Development Status :: 3 - Alpha
Classifier: Intended Audience :: Financial and Insurance Industry
Classifier: License :: OSI Approved :: MIT License
Classifier: Programming Language :: Python :: 3
Classifier: Programming Language :: Python :: 3.8
Classifier: Programming Language :: Python :: 3.9
Classifier: Programming Language :: Python :: 3.10
Classifier: Topic :: Office/Business :: Financial
Classifier: Topic :: Software Development :: Libraries :: Python Modules
Requires-Python: >=3.8
License-File: LICENSE
Requires-Dist: pandas>=1.3.0
Requires-Dist: requests>=2.26.0
Requires-Dist: beautifulsoup4>=4.9.3
Requires-Dist: lxml>=4.9.0
Requires-Dist: streamlit>=1.0.0
Dynamic: author
Dynamic: author-email
Dynamic: classifier
Dynamic: description
Dynamic: description-content-type
Dynamic: home-page
Dynamic: keywords
Dynamic: license-file
Dynamic: project-url
Dynamic: requires-dist
Dynamic: requires-python
Dynamic: summary
